email_listener/__init__.py
email_listener/email_processing.py
email_listener/email_responder.py
email_listener/experiment1.py
email_listener/experiment2.py
email_listener/experiment3.py
email_listener/helpers.py
email_listener-1.2.dist-info/LICENSE
email_listener-1.2.dist-info/METADATA
email_listener-1.2.dist-info/WHEEL
email_listener-1.2.dist-info/top_level.txt
email_listener-1.2.dist-info/RECORD
