Metadata-Version: 2.1
Name: email-listener
Version: 1.2
Summary: Listen in an email folder and process incoming emails.
Home-page: https://github.com/njdreikosen/email_listener
Author: Noah Dreikosen
Author-email: ndreikosen@gmail.com
License: GNU GPLv3
Platform: UNKNOWN
Classifier: Development Status :: 4 - Beta
Classifier: License :: OSI Approved :: GNU General Public License v3 (GPLv3)
Classifier: Programming Language :: Python :: 3.6
Classifier: Programming Language :: Python :: 3.7
Classifier: Programming Language :: Python :: 3.8
Classifier: Topic :: Communications :: Email
